diarize_whisper/__init__.py
diarize_whisper/__main__.py
diarize_whisper/asr.py
diarize_whisper/audio.py
diarize_whisper/cli.py
diarize_whisper/diarization.py
diarize_whisper/transcript.py
diarize_whisper-0.1.4.dist-info/METADATA
diarize_whisper-0.1.4.dist-info/WHEEL
diarize_whisper-0.1.4.dist-info/entry_points.txt
diarize_whisper-0.1.4.dist-info/top_level.txt
diarize_whisper-0.1.4.dist-info/RECORD
