Metadata-Version: 2.4
Name: diarize_whisper
Version: 0.1.4
Summary: Librairie pour la transcription ASR et la diarisation
Author: Samy Le Galloudec
Author-email: samy.legalloudec@gmail.com
Classifier: Programming Language :: Python :: 3
Classifier: License :: OSI Approved :: MIT License
Classifier: Operating System :: OS Independent
Requires-Python: >=3.10
Requires-Dist: pydub
Requires-Dist: torch
Requires-Dist: pyannote.audio
Requires-Dist: transformers
Dynamic: author
Dynamic: author-email
Dynamic: classifier
Dynamic: description
Dynamic: description-content-type
Dynamic: requires-dist
Dynamic: requires-python
Dynamic: summary
